{
  "checks": [
    {
      "timestamp": "2026-03-17T14:34:15.894Z",
      "symbol": "ASTER-PERP",
      "currentPrice": "0.6915",
      "gridRange": "$0.6 - $0.8",
      "activeLevels": 0,
      "potentialProfit": "0.00",
      "dailyEstimate": "0.00",
      "status": "IN_RANGE"
    },
    {
      "timestamp": "2026-03-17T14:39:15.964Z",
      "symbol": "ASTER-PERP",
      "currentPrice": "0.7127",
      "gridRange": "$0.6 - $0.8",
      "activeLevels": 2,
      "potentialProfit": "20.00",
      "dailyEstimate": "2.00",
      "status": "IN_RANGE"
    },
    {
      "timestamp": "2026-03-17T14:43:53.324Z",
      "symbol": "ASTER-PERP",
      "currentPrice": "0.6607",
      "gridRange": "$0.6 - $0.8",
      "activeLevels": 3,
      "grossProfit": "30.00",
      "fees": "0.30",
      "slippage": "0.30",
      "funding": "0.45",
      "netProfit": "28.95",
      "profitabilityAfterCosts": "96.5%",
      "breakEvenCycles": 1,
      "worstCaseLoss": "300.00",
      "riskRewardRatio": "0.097",
      "riskLevel": "LOW",
      "status": "IN_RANGE",
      "losingLevels": 3,
      "losingPercentage": "14.3%",
      "unrealizedLoss": "2.90",
      "simulationMode": true
    },
    {
      "timestamp": "2026-03-17T14:48:53.391Z",
      "symbol": "ASTER-PERP",
      "currentPrice": "0.6841",
      "gridRange": "$0.6 - $0.8",
      "activeLevels": 1,
      "grossProfit": "10.00",
      "fees": "0.10",
      "slippage": "0.10",
      "funding": "0.15",
      "netProfit": "9.65",
      "profitabilityAfterCosts": "96.5%",
      "breakEvenCycles": 1,
      "worstCaseLoss": "300.00",
      "riskRewardRatio": "0.032",
      "riskLevel": "LOW",
      "status": "IN_RANGE",
      "losingLevels": 1,
      "losingPercentage": "4.8%",
      "unrealizedLoss": "0.29",
      "simulationMode": true
    },
    {
      "timestamp": "2026-03-17T16:00:28.721Z",
      "symbol": "ASTER-PERP",
      "currentPrice": "0.6605",
      "gridRange": "$0.6 - $0.8",
      "activeLevels": 3,
      "grossProfit": "30.00",
      "fees": "0.30",
      "slippage": "0.30",
      "funding": "0.45",
      "netProfit": "28.95",
      "profitabilityAfterCosts": "96.5%",
      "breakEvenCycles": 1,
      "worstCaseLoss": "300.00",
      "riskRewardRatio": "0.097",
      "riskLevel": "LOW",
      "status": "IN_RANGE",
      "losingLevels": 3,
      "losingPercentage": "14.3%",
      "unrealizedLoss": "2.92",
      "simulationMode": true
    }
  ]
}